README.txt
setup.cfg
setup.py
lacdkeraspackage/__init__.py
lacdkeraspackage/dataprocessing.py
rcaisskeras/__init__.py
rcaisskeras/keras.py
rcaisskeras.egg-info/PKG-INFO
rcaisskeras.egg-info/SOURCES.txt
rcaisskeras.egg-info/dependency_links.txt
rcaisskeras.egg-info/top_level.txt