Metadata-Version: 1.0
Name: rcaisskeras
Version: 0.0.0.11
Summary: Rcaiss
Home-page: UNKNOWN
Author: HuangTeEn
Author-email: qaz910048@gmail.com
License: MIT
Keywords: Keras,Teach,rcaiss
Platform: UNKNOWN
